{"id":"_ctj4b85tapk","name":"gravesludge","traits":"Uncommon","level":12,"specials":[{"id":"_18c51urgzcg","name":"Wall of Ectoplasm","traits":"concentrate, evocation, necromancy, mental, negative","range":"","actions":"two","type":"defense","description":"This ability is very similar to the spell Wall of Ice save in these respects:  The wall has Fast Healing 10 and any 5 foot section that is breached closes in one round unless breached with positive energy.  The wall is immune to negative energy rather than cold, and weakness positive 15.  The remnants of a breached section do 2d6 negative rather than cold.  This wall also blocks ethereal and incorporeal travel.\nIn addition any creature approaching the wall within 10 feet must make a DC 30 Will Save or become Frightened 1 for 1 round, or Frightened 2 for 1 minute on a critical failure."},{"id":"_336mljrk4y0","name":"Create Spawn","traits":"divine, necromancy","range":"","actions":"none","type":"offense","description":"Any creature slain by a gravesludge rises as a juju zombie (applying said template, see book 2) with free will."}],"alignment":"ne","size":"medium","type":"ooze","adjust":0,"description":"","items":"","spellattack":{"value":"21","benchmark":"moderate","note":""},"spelldc":{"value":"29","benchmark":"moderate","note":""},"savenote":"","creature":"","speed":"25 ft., burrow 25 ft.","imgurl":"","spelltype":"divine innate","ritualtype":"","rituals":"","spells":["","","","","harm","","phantasmal killer (3)","","telekinetic maneuver (at will), death knell (3)","","ghost sound, telekinetic projectile"],"constant":"","strength":{"value":"8","benchmark":"extreme","note":""},"dexterity":{"value":"6","benchmark":"high","note":""},"constitution":{"value":"7","benchmark":"high","note":""},"intelligence":{"value":"5","benchmark":"moderate","note":""},"wisdom":{"value":"6","benchmark":"high","note":""},"charisma":{"value":"6","benchmark":"high","note":""},"perception":{"value":"22","benchmark":"moderate","note":"motion sense, lifesense 60 ft., no vision"},"acrobatics":{"value":"","benchmark":"moderate","note":""},"arcana":{"value":"","benchmark":"moderate","note":""},"athletics":{"value":"25","benchmark":"high","note":""},"crafting":{"value":"","benchmark":"moderate","note":""},"deception":{"value":"","benchmark":"moderate","note":""},"diplomacy":{"value":"","benchmark":"moderate","note":""},"intimidation":{"value":"","benchmark":"moderate","note":""},"medicine":{"value":"","benchmark":"moderate","note":""},"nature":{"value":"","benchmark":"moderate","note":""},"occultism":{"value":"","benchmark":"moderate","note":""},"performance":{"value":"","benchmark":"moderate","note":""},"religion":{"value":"20","benchmark":"low","note":""},"society":{"value":"","benchmark":"moderate","note":""},"stealth":{"value":"24","benchmark":"moderate","note":""},"survival":{"value":"","benchmark":"moderate","note":""},"thievery":{"value":"","benchmark":"moderate","note":""},"lore":{"value":"","benchmark":"moderate","note":"","name":"lore"},"lorealt":{"value":"","benchmark":"moderate","note":"","name":"lore"},"ac":{"value":"32","benchmark":"moderate","note":""},"hp":{"value":"260","benchmark":"high","note":"negative healing"},"fortitude":{"value":"21","benchmark":"moderate","note":""},"reflex":{"value":"25","benchmark":"high","note":""},"will":{"value":"20","benchmark":"low","note":""},"resistance":{"value":"","benchmark":"moderate","note":""},"weakness":{"value":"13 Good","benchmark":"moderate","note":""},"immunity":{"value":"critical hits, precision, unconscious, acid, cold, negative, death effects, sleep","benchmark":"moderate","note":""},"roadmap":"","strikes":[{"id":"_1h0ypke2glu","name":"slime slap","traits":"","attack":"24","damage":"3d8+10 bludgeoning plus 2d6 negative and 1d6 negative persistant","type":"Melee"}],"hints":["perception","strength","dexterity","constitution","intelligence","wisdom","charisma","ac","fortitude","reflex","will","hp"],"languages":"common, telepathy 100 ft."}